atlas_asset_client/__init__.py
atlas_asset_client-0.3.4.dist-info/licenses/LICENSE
atlas_asset_http_client_python/__init__.py
atlas_asset_http_client_python/components.py
atlas_asset_http_client_python/http_client.py
atlas_asset_client-0.3.4.dist-info/METADATA
atlas_asset_client-0.3.4.dist-info/WHEEL
atlas_asset_client-0.3.4.dist-info/top_level.txt
atlas_asset_client-0.3.4.dist-info/RECORD
