Metadata-Version: 2.4
Name: atlas-asset-client
Version: 0.3.4
Summary: Async HTTP client for Atlas Command.
Author: ATLAS Team
License-Expression: MIT
Project-URL: Homepage, https://github.com/atlas/command
Project-URL: Repository, https://github.com/atlas/command
Project-URL: Documentation, https://github.com/atlas/command/wiki
Keywords: atlas,command,http,asset
Classifier: Development Status :: 4 - Beta
Classifier: Intended Audience :: Developers
Classifier: Topic :: System :: Monitoring
Classifier: Topic :: Software Development :: Libraries
Classifier: Programming Language :: Python :: 3.9
Classifier: Programming Language :: Python :: 3.10
Classifier: Programming Language :: Python :: 3.11
Classifier: Programming Language :: Python :: 3.12
Classifier: Programming Language :: Python :: 3.13
Requires-Python: <3.14,>=3.9
License-File: LICENSE
Requires-Dist: httpx>=0.27
Provides-Extra: dev
Requires-Dist: pytest>=8.0.0; extra == "dev"
Requires-Dist: pytest-asyncio>=0.21.0; extra == "dev"
Requires-Dist: pytest-cov>=4.1.0; extra == "dev"
Requires-Dist: mypy>=1.10.0; extra == "dev"
Dynamic: license-file
